quickindex/__init__.py
quickindex/quickindex.py
quickindex-1.1.0.dist-info/METADATA
quickindex-1.1.0.dist-info/WHEEL
quickindex-1.1.0.dist-info/licenses/LICENSE
quickindex-1.1.0.dist-info/RECORD
