Metadata-Version: 2.1
Name: quickindex
Version: 1.1.0
Summary: An easy way to index lists in python
Project-URL: Homepage, https://github.com/dbernadett/quickindex
Project-URL: Bug Tracker, https://github.com/dbernadett/quickindex/issues
Author-email: David Bernadett <djbernadett@gmail.com>
License-File: LICENSE
Classifier: License :: OSI Approved :: MIT License
Classifier: Operating System :: OS Independent
Classifier: Programming Language :: Python :: 3
Requires-Python: >=3.7
